{
  "vibe": "Сегодня код пишется сам, кофе наливается волшебным образом, а дедлайны убегают от вас, как офисные тараканы от света.",
  "predictions": [
    {
      "sign": "Овен",
      "body": "Твой код сегодня компилируется с первого раза, а коллеги внезапно соглашаются со всеми твоими идеями.",
      "twist": "Оказалось, твой монитор обладает гипнотическими способностями — теперь все видят мир твоими глазами.",
      "advice": "Выпей кофе с щепоткой корицы — это придаст тебе скорости, как горячей клавише F5."
    },
    {
      "sign": "Телец",
      "body": "Твой стол сегодня превратился в оазис продуктивности: даже крошки от печенья выстраиваются в идеальные ряды.",
      "twist": "Твой термос начал подогревать еду силой твоего желания — теперь обед всегда идеальной температуры.",
      "advice": "Сделай паузу и выпей чай с мёдом — даже серверы иногда нуждаются в перезагрузке."
    },
    {
      "sign": "Близнецы",
      "body": "Твои сообщения в чате сегодня читаются как увлекательный роман, а эмодзи оживают и танцуют на экране.",
      "twist": "Твой наушник внезапно заиграл ту самую песню, о которой ты только что подумал.",
      "advice": "Кофе с кардамоном — секрет твоего сегодняшнего вдохновения."
    },
    {
      "sign": "Рак",
      "body": "Твой список задач сегодня сокращается сам, а почта отвечает на письма без твоего участия.",
      "twist": "Офисный кактус расцвёл в знак поддержки — теперь он твой личный мотиватор.",
      "advice": "Чай с ромашкой успокоит даже самый горячий дедлайн."
    },
    {
      "sign": "Лев",
      "body": "Твоя презентация сегодня покорила даже кофемашину — она выдала тебе двойной эспрессо без очереди.",
      "twist": "Твой бейдж засветился, как маяк, и теперь все идут к тебе за советом.",
      "advice": "Выпей латте с золотой пенкой — сегодня ты король офиса."
    },
    {
      "sign": "Дева",
      "body": "Твой Excel сегодня предсказывает будущее, а формулы решаются сами собой.",
      "twist": "Твой степлер начал скреплять листы идеально ровно — даже линейка завидует.",
      "advice": "Мятный чай поможет сохранить холодную голову в горячих спорах."
    },
    {
      "sign": "Весы",
      "body": "Твои переговоры сегодня проходят так гладко, что даже принтер перестал зажевывать бумагу.",
      "twist": "Твой график работы внезапно синхронизировался с твоим биоритмом — теперь ты всегда в потоке.",
      "advice": "Капучино с корицей — идеальный баланс, как и ты."
    },
    {
      "sign": "Скорпион",
      "body": "Твой код сегодня исправляет баги сам, а коллеги чувствуют твоё присутствие, даже если ты в другом чате.",
      "twist": "Твой курсор начал мигать в такт твоему сердцебиению — теперь все знают, когда ты взволнован.",
      "advice": "Чёрный кофе с щепоткой соли — для тех, кто любит остроту."
    },
    {
      "sign": "Стрелец",
      "body": "Твой мозговой штурм сегодня выходит за пределы офиса — даже голуби на подоконнике кивают в такт.",
      "twist": "Твой скриншот случайно сохранился как шедевр современного искусства.",
      "advice": "Чай с имбирём — для тех, кто летит вперёд на всех парах."
    },
    {
      "sign": "Козерог",
      "body": "Твой план на день выполняется с точностью до миллисекунды, а кофе остывает ровно настолько, чтобы ты мог его пить.",
      "twist": "Твой ежедневник начал писать заметки за тебя — и почерк у него идеальный.",
      "advice": "Эспрессо без сахара — для тех, кто ценит чистоту и эффективность."
    },
    {
      "sign": "Водолей",
      "body": "Твои идеи сегодня витают в воздухе, и коллеги ловят их, как конфетти.",
      "twist": "Твой монитор отражает не только экран, но и твои самые смелые мечты.",
      "advice": "Кофе с сиропом лаванды — для вдохновения и лёгкости."
    },
    {
      "sign": "Рыбы",
      "body": "Твой чат сегодня наполнен тёплыми словами, а смайлики оживают и подмигивают тебе.",
      "twist": "Твой стакан воды сам наполняется, когда ты задумываешься.",
      "advice": "Чай с жасмином — для тех, кто плывёт по течению с улыбкой."
    }
  ],
  "date": "2026-06-25",
  "generated_at": "2026-06-25T10:18:11.342465Z"
}