{
  "vibe": "Сегодня код пишется сам, кофе варится с улыбкой, а дедлайны убегают от вас в панике.",
  "predictions": [
    {
      "sign": "Овен",
      "body": "Ты сегодня настолько продуктивен, что твой курсор бегает по экрану быстрее, чем коллеги успевают пить кофе.",
      "twist": "Внезапно твой стул превратился в электрокар, и теперь ты объезжаешь офис с ветерком.",
      "advice": "Выпей эспрессо и представь, что это топливо для твоего нового транспорта."
    },
    {
      "sign": "Телец",
      "body": "Твоя клавиатура сегодня печатает только гениальные идеи, даже когда ты просто смотришь на неё.",
      "twist": "Оказалось, твой монитор — это портал в мир, где дедлайны всегда соблюдаются.",
      "advice": "Завари чай с мёдом и наблюдай, как баги исправляются сами."
    },
    {
      "sign": "Близнецы",
      "body": "Ты сегодня говоришь настолько убедительно, что даже принтер согласился печатать без жалоб.",
      "twist": "Твои Slack-сообщения начали появляться у коллег до того, как ты их отправил.",
      "advice": "Сделай перерыв и пообщайся с кофемашиной — у неё отличное чувство юмора."
    },
    {
      "sign": "Рак",
      "body": "Твои таблицы Excel сегодня настолько идеальны, что даже бухгалтерия заплакала от умиления.",
      "twist": "Внезапно твой ноутбук начал показывать котиков вместо ошибок 404.",
      "advice": "Пей латте с корицей и представляй, что это волшебный эликсир порядка."
    },
    {
      "sign": "Лев",
      "body": "Ты сегодня так уверен в себе, что даже Wi-Fi подключается к тебе быстрее, чем к остальным.",
      "twist": "Твой голос в Zoom стал настолько харизматичным, что коллеги начали аплодировать после каждого предложения.",
      "advice": "Закажи капучино с рисунком льва — сегодня твой день."
    },
    {
      "sign": "Дева",
      "body": "Твой to-do list сегодня сокращается сам, потому что Вселенная решила помочь тебе с сортировкой задач.",
      "twist": "Офисные растения начали цвести каждый раз, когда ты проходишь мимо.",
      "advice": "Выпей матчу и наслаждайся моментом, когда всё идёт по плану."
    },
    {
      "sign": "Весы",
      "body": "Ты сегодня настолько гармоничен, что даже конфликты в чатах разрешаются сами собой.",
      "twist": "Твой стакан воды превратился в бесконечный источник идеального баланса pH.",
      "advice": "Попробуй чай с лепестками роз — сегодня он обладает магией компромисса."
    },
    {
      "sign": "Скорпион",
      "body": "Ты сегодня настолько проницателен, что видишь баги в коде ещё до их появления.",
      "twist": "Твой взгляд настолько мощный, что кофе в кружке коллег начал закипать от одного твоего взгляда.",
      "advice": "Выпей чёрный кофе и наслаждайся своей таинственной аурой."
    },
    {
      "sign": "Стрелец",
      "body": "Ты сегодня настолько энергичен, что даже серверы начали работать быстрее, когда ты рядом.",
      "twist": "Твои шутки в чате настолько хороши, что босс предложил тебе stand-up в перерыве.",
      "advice": "Закажи раф с сиропом — сегодня твой юмор должен быть сладким."
    },
    {
      "sign": "Козерог",
      "body": "Ты сегодня настолько организован, что даже пылинки на столе выстроились в идеальный ряд.",
      "twist": "Твой план на день стал настолько чётким, что время начало подстраиваться под тебя.",
      "advice": "Выпей эспрессо и наблюдай, как Вселенная аплодирует твоей дисциплине."
    },
    {
      "sign": "Водолей",
      "body": "Ты сегодня настолько креативен, что даже кофеварка начала варить напитки с неожиданными вкусами.",
      "twist": "Твой мозг выдал столько идей, что они материализовались в виде конфет на твоём столе.",
      "advice": "Попробуй холодный brew — сегодня он может быть голубого цвета."
    },
    {
      "sign": "Рыбы",
      "body": "Ты сегодня настолько интуитивен, что понимаешь, что хочет сказать клиент, ещё до его письма.",
      "twist": "Твой стакан с водой начал показывать мини-радугу каждый раз, когда ты берёшь паузу.",
      "advice": "Завари чай с ромашкой и слушай, о чём шепчутся дедлайны."
    }
  ],
  "date": "2026-06-06",
  "generated_at": "2026-06-06T09:28:56.182649Z"
}